nice_server_api/__init__.py
nice_server_api/client.py
nice_server_api/server.py
nice_server_api/utils.py
nice_server_api-0.1.0.dist-info/licenses/LICENSE
nice_server_api-0.1.0.dist-info/METADATA
nice_server_api-0.1.0.dist-info/WHEEL
nice_server_api-0.1.0.dist-info/top_level.txt
nice_server_api-0.1.0.dist-info/RECORD
