Metadata-Version: 2.4
Name: nice-server-api
Version: 0.1.0
Summary: Библиотека для упрощения работы с серверной (Flask) и клиентской (requests) частями API
Author-email: Iroslav <co2banan@gmail.com>
Project-URL: Homepage, https://github.com/kiber-banan/NiceServerAPI
Project-URL: Bug Tracker, https://github.com/kiber-banan/NiceServerAPI/issues
Classifier: Programming Language :: Python :: 3
Classifier: License :: OSI Approved :: MIT License
Classifier: Operating System :: OS Independent
Requires-Python: >=3.6
License-File: LICENSE
Requires-Dist: flask>=2.0.0
Requires-Dist: requests>=2.25.0
Dynamic: license-file
